keepyourdate/__init__.py
keepyourdate/check.py
keepyourdate/edit.py
keepyourdate-0.0.3.dist-info/LICENSE
keepyourdate-0.0.3.dist-info/METADATA
keepyourdate-0.0.3.dist-info/WHEEL
keepyourdate-0.0.3.dist-info/top_level.txt
keepyourdate-0.0.3.dist-info/RECORD
