Metadata-Version: 2.1
Name: keepyourdate
Version: 0.0.3
Summary: Simple daily event keeper.
Home-page: https://github.com/zizardev/keepyourdate
Author: Mishalov_Bogdan
Author-email: bogdanmissss@gmail.com
Project-URL: GitHub, https://github.com/zizardev/keepyourdate
Keywords: calendar keep date
Classifier: Programming Language :: Python :: 3.11
Classifier: License :: OSI Approved :: MIT License
Classifier: Operating System :: OS Independent
Requires-Python: >=3.6
License-File: LICENSE
